[
  [
    {
      "Country": "EU28",
      "value": 65.7
    },
    {
      "Country": "BE",
      "value": 65.3
    },
    {
      "Country": "BG",
      "value": 42.7
    },
    {
      "Country": "CZ",
      "value": 57.3
    },
    {
      "Country": "DK",
      "value": 83.1
    },
    {
      "Country": "DE",
      "value": 65
    },
    {
      "Country": "EE",
      "value": 74.7
    },
    {
      "Country": "IE",
      "value": 74.2
    },
    {
      "Country": "EL",
      "value": 44.7
    },
    {
      "Country": "ES",
      "value": 64
    },
    {
      "Country": "FR",
      "value": 67.3
    },
    {
      "Country": "HR",
      "value": 51
    },
    {
      "Country": "IT",
      "value": 59.3
    },
    {
      "Country": "CY",
      "value": 51.3
    },
    {
      "Country": "LV",
      "value": 65.8
    },
    {
      "Country": "LT",
      "value": 50.6
    },
    {
      "Country": "LU",
      "value": 69.1
    },
    {
      "Country": "HU",
      "value": 54.3
    },
    {
      "Country": "MT",
      "value": 64.2
    },
    {
      "Country": "NL",
      "value": 83.9
    },
    {
      "Country": "AT",
      "value": 61.2
    },
    {
      "Country": "PL",
      "value": 52.5
    },
    {
      "Country": "PT",
      "value": 47.5
    },
    {
      "Country": "RO",
      "value": 50.3
    },
    {
      "Country": "SI",
      "value": 72.9
    },
    {
      "Country": "SK",
      "value": 46.3
    },
    {
      "Country": "FI",
      "value": 77.4
    },
    {
      "Country": "SE",
      "value": 90.1
    },
    {
      "Country": "UK",
      "value": 69.9
    }
  ]
]